PyImageConverter/PyImageConverter.py
PyImageConverter/SAMPLE_convert.py
PyImageConverter/__init__.py
PyImageConverter-1.0.0.dist-info/METADATA
PyImageConverter-1.0.0.dist-info/WHEEL
PyImageConverter-1.0.0.dist-info/entry_points.txt
PyImageConverter-1.0.0.dist-info/top_level.txt
PyImageConverter-1.0.0.dist-info/zip-safe
PyImageConverter-1.0.0.dist-info/RECORD
